{"_classe":"stdClass","id":7,"lote":10,"nf":15,"cnpj":"47626510000132","serie":0,"pais":"Brasil","municipio":"SAO JOSE DO RIO PRETO","nome":"Agro Fauna Matriz","ie":"647097432115","crt":3,"cep":"15055000","telefone":"1122552255","bairro":"jd a alegre","logadouro":"RUA COUTINHO CAVALCANTI","numero":"1171","logo":"http://192.168.18.121:888/novo_rtc_web/php/uploads/logo_1555347399263.txt","estado":"SP","certificado":"http://189.50.142.58/php/uploads/arquivo_rnkhpbxwroyrdefipcjgzgzfyjczxbrmtfgengvp.pfx","senha_certificado":12345678,"acao":"EMITIR","pedido":36802,"operacao":"Venda de mercadoria fora do estado","cfop":6102,"saida_entrada":true,"finalidade":1,"consumidor":0,"frete":0,"frete_cif_fob":false,"suframado":false,"volumes":2,"informacoes_adcionais":"Os produtos estao adequadamente acondicionados para suportar os riscos normais das etapas RESERVADO AO FISCO necessarias a uma operacao de transporte e que atende a regulamentacao em vigor. Conf. Lei n. 9974 de 06/06/00 reg. pelo decreto 4072/02 de 04/01/2002, as embalagens adquiridas nesta NF deverao ser devolvidas no prazo de 1 (um) ano, perfuradas e com a triplice lavagem realizada, na unidade de recebimento: Agro-Fauna Com. Ins. Ltda. R.Coutinho Cavalcanti, 1171 - Jd Alto Alegre - S J Rio Preto-SP. CENTRAL DE RECEBIMENTOS DE EMBALAGENS VAZIAS DE AGROTOXICOS Av Jose Geraldo de Matos, 765A Distrito Industrial do Paracangua  - Taubate  SP Nota referente a pedido 9133. Problema de emissao: Rejeicao: Aliquota de ICMS superior a definida para a operacao interestadual [nItem:1]","destinatario":{"_classe":"stdClass","id":47331,"estado":"GO","cnpj":"08345328000151","nome":"Base Comercio de Produtos Agricolas LTDA ME","bairro":"nao cadastrado","logadouro":"nao cadastrado","numero":"nao cadastrado","municipio":"MORRINHOS GO","cep":"75650000","pais":"Brasil","telefone":"6434134588","ie":"104046252","email":"rtc@rtc.com.br"},"transportadora":{"_classe":"stdClass","id":2744530,"cnpj":"82110818000393","nome":"ALFA TRANSPORTES EIRELI","ie":"336829364119","endereco":"Av.Recife","municipio":"SAO PAULO","estado":"SP"},"produtos":[{"_classe":"stdClass","codigo":471121,"ncm":"38089199","unidade":"Frc","nome":"Decis 25 EC (Frc 1L)","quantidade":24,"valor":54.21,"informacao_adcional":"Validade: 12/05/54379.Lote: 16570 - Qtd: 12Lote: 16570 - Qtd: 12","pesoB":1.05,"pesoL":1,"ipi":0,"reducao_base_calculo":60,"icms":7}],"vencimentos":[{"_classe":"stdClass","data":1555347499327,"valor":1301.04}]}