{"_classe":"stdClass","id":7,"lote":545,"nf":483,"cnpj":"47626510000132","serie":0,"pais":"Brasil","municipio":"SAO JOSE DO RIO PRETO","nome":"Agro Fauna Matriz","ie":"647097432115","crt":3,"cep":"15055300","telefone":"1732241233","bairro":"Jd Alto Alegre","logadouro":"R Dr. Coutinho Cavalcante 1171","numero":"1171","logo":"http://192.168.18.121:888/novo_rtc_web/php/uploads/logo_1558986043730.txt","estado":"SP","certificado":"http://189.50.142.58/php/uploads/arquivo_rnkhpbxwroyrdefipcjgzgzfyjczxbrmtfgengvp.pfx","senha_certificado":12345678,"acao":"EMITIR","pedido":38224,"operacao":"Venda de merc destinada a zona franca de manaus","cfop":6110,"saida_entrada":true,"finalidade":1,"consumidor":0,"frete":0,"frete_cif_fob":true,"suframado":true,"inscricao_suframa":"110417500","volumes":42,"informacoes_adcionais":"Os produtos estao adequadamente acondicionados para suportar os riscos normais das etapas necessarias a uma operacao de transporte e que atende a regulamentacao em vigor. Conf. Lei n. 9974 de 06 06 00 reg. pelo decreto 4072 02 de 04 01 2002, as embalagens adquiridas nesta NF deverao ser devolvidas no prazo de 1 (um) ano, perfuradas e com a triplice lavagem realizada, na unidade de recebimento: Agro-Fauna Com. Ins. Ltda. R.Coutinho Cavalcanti, 1171 - Jd Alto Alegre - S J Rio Preto-SP. ARIA - ASSOC DE REVENDEDORES DE INSUMOS AGROPECUARIOS Rua Gino Cecconi, 400 Distrito Industrial Carlos de Arnaldo Silva - Sao Jose do Rio Preto SP Declaro que os produtos perigosos estao adequadamente classificados, embalados, identificados, e estivados para suportar os riscos das operacoes de transporte e que atendem as exigencias da regulamentacal BASE DE CALCULO DO ICMS REDUZIDA EM 60% CONFORME CONVENIO 100/97 - IPI ALIQUOTA ZERO. Pedido: 9589.Reducao da base de calculo conforme artigo 9 Anexo ll do Decreto 45.490 00 do RICMS SP. Isento conforme artigo 41 Item I do Anexo I do Decreto 45490 00 do RICMS-SP. Suframa: 110417500","destinatario":{"_classe":"stdClass","id":289835,"estado":"AP","cnpj":"01744208000188","nome":"Hernandes   Cia Ltda EPP","bairro":"Pacoval","logadouro":"R: Guanabara","numero":"959","municipio":"MACAPA","cep":"68908360","pais":"Brasil","telefone":"9632233186","ie":"030190762","email":"rtc@rtc.com.br","inscricao_suframa":"110417500"},"transportadora":{"_classe":"stdClass","id":2744939,"cnpj":"06186733000220","nome":"Exata Cargo LTDA","ie":"336942124118","endereco":"Av. Papa Joao Paulo I","municipio":"GUARULHOS","estado":"SP"},"produtos":[{"_classe":"stdClass","codigo":471121,"ncm":"38089199","unidade":"Frc","nome":"Decis 25 EC (Frc 1L)","quantidade":24,"valor":63.78,"informacao_adcional":"Cl Risco: 6.1. ONU 3351 Pest base de Piretroide, liq,Tox,Infl(deltametrina/sol aromatico), N.E. PIRETROIDE SINTETICO IIILOTES(S): D. Validade: 30/10/2022 022189960 (Qtd: 12)022189960 (Qtd: 12)","pesoB":1.05,"pesoL":1,"ipi":0,"reducao_base_calculo":60,"icms":0,"sem_icms":true},{"_classe":"stdClass","codigo":471120,"ncm":"38089199","unidade":"Frc","nome":"Decis 25 EC (Frc 250ml)","quantidade":40,"valor":18.54,"informacao_adcional":"Cl Risco: 6.1. ONU 3351 Pest base de Piretroide, liq,Tox,Infl(deltametrina/sol aromatico), N.E. PIRETROIDE SINTETICO lllLOTES(S): D. Validade: 30/07/2022 005189990 (Qtd: 20)005189990 (Qtd: 20)","pesoB":0.26,"pesoL":0.25,"ipi":0,"reducao_base_calculo":60,"icms":0,"sem_icms":true},{"_classe":"stdClass","codigo":471250,"ncm":"38089299","unidade":"Frc","nome":"Roundup Original DI (Frc 1L)","quantidade":300,"valor":23.07,"informacao_adcional":"Cl Risco: 0. ONU 0 Herbicida nao seletivo de acao sistemica do grupo quimico glicina subs, N.E. 445 g/L Glifosato LOTES(S): D. Validade: 30/01/2024 0028197280 (Qtd: 12)0028197280 (Qtd: 12)0028197280 (Qtd: 12)0028197280 (Qtd: 12)0028197280 (Qtd: 12)0028197280 (Qtd: 12)0028197280 (Qtd: 12)0028197280 (","pesoB":1.05,"pesoL":1,"ipi":0,"reducao_base_calculo":60,"icms":0,"sem_icms":true},{"_classe":"stdClass","codigo":471258,"ncm":"38089299","unidade":"Gl","nome":"Roundup Original DI (Gl 5L)","quantidade":16,"valor":110.64,"informacao_adcional":"Cl Risco: 0. ONU 0 Prod nao enq na port em vigor sobre transp de prod perigosos, N.E. 445 g/L Glifosato LOTES(S): D. Validade: 30/01/2024 02851838400 (Qtd: 4)02851838400 (Qtd: 4)02851838400 (Qtd: 4)02851838400 (Qtd: 4)","pesoB":5.99,"pesoL":5.7,"ipi":0,"reducao_base_calculo":60,"icms":0,"sem_icms":true},{"_classe":"stdClass","codigo":471252,"ncm":"38089321","unidade":"Gl","nome":"Pampa (Gl 5L)","quantidade":4,"valor":126.53,"informacao_adcional":"Cl Risco: 6.1. ONU 2902 PESTICIDA LIQ., TOXICO, N.E. (PICLORAM, 2,4-D), N.E. 2,4D 406g/L+ Picloram 103g/L SL IILOTES(S): D. Validade: 30/06/2021 0291727280 (Qtd: 4)","pesoB":5.25,"pesoL":5,"ipi":0,"reducao_base_calculo":60,"icms":0,"sem_icms":true},{"_classe":"stdClass","codigo":471277,"ncm":"85365090","unidade":"Frc","nome":"Wil Fix (Frc 1 lt) Espalhante Adesivo.","quantidade":48,"valor":8.85,"informacao_adcional":"Cl Risco: 0. ONU 0 , N.E.  LOTES(S): D. Validade: 30/08/2022 22082000 (Qtd: 12)22082000 (Qtd: 12)22082000 (Qtd: 12)22082000 (Qtd: 12)","pesoB":1.05,"pesoL":1,"ipi":0,"reducao_base_calculo":60,"icms":0,"sem_icms":true},{"_classe":"stdClass","codigo":471273,"ncm":"38089197","unidade":"Frc","nome":"Oleo Mineral Agefix (Frc 1L)","quantidade":48,"valor":13.34,"informacao_adcional":"Cl Risco: 0. ONU 0 NAO CLASSIFICADO COMO PERIGOSO PARA TRANSPORTE, N.E. Oleo Mineral lllLOTES(S): D. Validade: 28/02/2021 041fix/19 (Qtd: 12)041fix/19 (Qtd: 12)041fix/19 (Qtd: 12)041fix/19 (Qtd: 12)","pesoB":1.05,"pesoL":1,"ipi":0,"reducao_base_calculo":60,"icms":0,"sem_icms":true}],"vencimentos":[{"_classe":"stdClass","data":1561557295000,"valor":12534.8}]}